[
  {
    "timestamp": 0,
    "metrics": {
      "Timestamp": 175588.020375,
      "AudioHandlers": 0,
      "AudioWorkletProcessors": 0,
      "Documents": 32,
      "Frames": 33,
      "JSEventListeners": 1909,
      "LayoutObjects": 3183,
      "MediaKeySessions": 0,
      "MediaKeys": 0,
      "Nodes": 3875,
      "Resources": 280,
      "ContextLifecycleStateObservers": 125,
      "V8PerContextDatas": 15,
      "WorkerGlobalScopes": 1,
      "UACSSResources": 0,
      "RTCPeerConnections": 0,
      "ResourceFetchers": 34,
      "AdSubframes": 0,
      "DetachedScriptStates": 5,
      "ArrayBufferContents": 619,
      "LayoutCount": 0,
      "RecalcStyleCount": 0,
      "LayoutDuration": 0,
      "RecalcStyleDuration": 0,
      "DevToolsCommandDuration": 0.000139,
      "ScriptDuration": 0,
      "V8CompileDuration": 0,
      "TaskDuration": 0.000172,
      "TaskOtherDuration": 3.3e-05,
      "ThreadTime": 0.000241,
      "ProcessTime": 5.135037,
      "JSHeapUsedSize": 69122332,
      "JSHeapTotalSize": 90849280,
      "FirstMeaningfulPaint": 175581.710988,
      "DomContentLoaded": 175581.346685,
      "NavigationStart": 175577.658679
    }
  },
  {
    "timestamp": 1,
    "metrics": {
      "Timestamp": 175589.026138,
      "AudioHandlers": 0,
      "AudioWorkletProcessors": 0,
      "Documents": 32,
      "Frames": 33,
      "JSEventListeners": 1912,
      "LayoutObjects": 3183,
      "MediaKeySessions": 0,
      "MediaKeys": 0,
      "Nodes": 3875,
      "Resources": 284,
      "ContextLifecycleStateObservers": 126,
      "V8PerContextDatas": 15,
      "WorkerGlobalScopes": 1,
      "UACSSResources": 0,
      "RTCPeerConnections": 0,
      "ResourceFetchers": 34,
      "AdSubframes": 0,
      "DetachedScriptStates": 5,
      "ArrayBufferContents": 619,
      "LayoutCount": 0,
      "RecalcStyleCount": 0,
      "LayoutDuration": 0,
      "RecalcStyleDuration": 0,
      "DevToolsCommandDuration": 0.000375,
      "ScriptDuration": 0.018101,
      "V8CompileDuration": 2e-05,
      "TaskDuration": 0.035572,
      "TaskOtherDuration": 0.017076,
      "ThreadTime": 0.038748,
      "ProcessTime": 5.190473,
      "JSHeapUsedSize": 69641232,
      "JSHeapTotalSize": 90849280,
      "FirstMeaningfulPaint": 175581.710988,
      "DomContentLoaded": 175581.346685,
      "NavigationStart": 175577.658679
    }
  },
  {
    "timestamp": 2,
    "metrics": {
      "Timestamp": 175590.030011,
      "AudioHandlers": 0,
      "AudioWorkletProcessors": 0,
      "Documents": 32,
      "Frames": 33,
      "JSEventListeners": 1912,
      "LayoutObjects": 3183,
      "MediaKeySessions": 0,
      "MediaKeys": 0,
      "Nodes": 3875,
      "Resources": 284,
      "ContextLifecycleStateObservers": 126,
      "V8PerContextDatas": 15,
      "WorkerGlobalScopes": 1,
      "UACSSResources": 0,
      "RTCPeerConnections": 0,
      "ResourceFetchers": 34,
      "AdSubframes": 0,
      "DetachedScriptStates": 5,
      "ArrayBufferContents": 619,
      "LayoutCount": 0,
      "RecalcStyleCount": 0,
      "LayoutDuration": 0,
      "RecalcStyleDuration": 0,
      "DevToolsCommandDuration": 0.000685,
      "ScriptDuration": 0.028096,
      "V8CompileDuration": 2e-05,
      "TaskDuration": 0.054875,
      "TaskOtherDuration": 0.026074,
      "ThreadTime": 0.059918,
      "ProcessTime": 5.221622,
      "JSHeapUsedSize": 69868684,
      "JSHeapTotalSize": 90849280,
      "FirstMeaningfulPaint": 175581.710988,
      "DomContentLoaded": 175581.346685,
      "NavigationStart": 175577.658679
    }
  },
  {
    "timestamp": 3,
    "metrics": {
      "Timestamp": 175591.033496,
      "AudioHandlers": 0,
      "AudioWorkletProcessors": 0,
      "Documents": 32,
      "Frames": 33,
      "JSEventListeners": 1912,
      "LayoutObjects": 3183,
      "MediaKeySessions": 0,
      "MediaKeys": 0,
      "Nodes": 3875,
      "Resources": 285,
      "ContextLifecycleStateObservers": 126,
      "V8PerContextDatas": 15,
      "WorkerGlobalScopes": 1,
      "UACSSResources": 0,
      "RTCPeerConnections": 0,
      "ResourceFetchers": 34,
      "AdSubframes": 0,
      "DetachedScriptStates": 5,
      "ArrayBufferContents": 619,
      "LayoutCount": 0,
      "RecalcStyleCount": 0,
      "LayoutDuration": 0,
      "RecalcStyleDuration": 0,
      "DevToolsCommandDuration": 0.00102,
      "ScriptDuration": 0.037203,
      "V8CompileDuration": 2e-05,
      "TaskDuration": 0.06734,
      "TaskOtherDuration": 0.029097,
      "ThreadTime": 0.073958,
      "ProcessTime": 5.239881,
      "JSHeapUsedSize": 70057076,
      "JSHeapTotalSize": 90849280,
      "FirstMeaningfulPaint": 175581.710988,
      "DomContentLoaded": 175581.346685,
      "NavigationStart": 175577.658679
    }
  },
  {
    "timestamp": 4,
    "metrics": {
      "Timestamp": 175592.038918,
      "AudioHandlers": 0,
      "AudioWorkletProcessors": 0,
      "Documents": 32,
      "Frames": 33,
      "JSEventListeners": 1912,
      "LayoutObjects": 3183,
      "MediaKeySessions": 0,
      "MediaKeys": 0,
      "Nodes": 3875,
      "Resources": 286,
      "ContextLifecycleStateObservers": 126,
      "V8PerContextDatas": 15,
      "WorkerGlobalScopes": 1,
      "UACSSResources": 0,
      "RTCPeerConnections": 0,
      "ResourceFetchers": 34,
      "AdSubframes": 0,
      "DetachedScriptStates": 5,
      "ArrayBufferContents": 619,
      "LayoutCount": 0,
      "RecalcStyleCount": 0,
      "LayoutDuration": 0,
      "RecalcStyleDuration": 0,
      "DevToolsCommandDuration": 0.001355,
      "ScriptDuration": 0.0456,
      "V8CompileDuration": 2e-05,
      "TaskDuration": 0.080792,
      "TaskOtherDuration": 0.033817,
      "ThreadTime": 0.088929,
      "ProcessTime": 5.260631,
      "JSHeapUsedSize": 70184428,
      "JSHeapTotalSize": 90849280,
      "FirstMeaningfulPaint": 175581.710988,
      "DomContentLoaded": 175581.346685,
      "NavigationStart": 175577.658679
    }
  },
  {
    "timestamp": 5,
    "metrics": {
      "Timestamp": 175593.043209,
      "AudioHandlers": 0,
      "AudioWorkletProcessors": 0,
      "Documents": 32,
      "Frames": 33,
      "JSEventListeners": 1912,
      "LayoutObjects": 3183,
      "MediaKeySessions": 0,
      "MediaKeys": 0,
      "Nodes": 3875,
      "Resources": 287,
      "ContextLifecycleStateObservers": 126,
      "V8PerContextDatas": 15,
      "WorkerGlobalScopes": 1,
      "UACSSResources": 0,
      "RTCPeerConnections": 0,
      "ResourceFetchers": 34,
      "AdSubframes": 0,
      "DetachedScriptStates": 5,
      "ArrayBufferContents": 619,
      "LayoutCount": 0,
      "RecalcStyleCount": 0,
      "LayoutDuration": 0,
      "RecalcStyleDuration": 0,
      "DevToolsCommandDuration": 0.001723,
      "ScriptDuration": 0.055164,
      "V8CompileDuration": 2e-05,
      "TaskDuration": 0.094768,
      "TaskOtherDuration": 0.037861,
      "ThreadTime": 0.104188,
      "ProcessTime": 5.283812,
      "JSHeapUsedSize": 70366852,
      "JSHeapTotalSize": 90849280,
      "FirstMeaningfulPaint": 175581.710988,
      "DomContentLoaded": 175581.346685,
      "NavigationStart": 175577.658679
    }
  },
  {
    "timestamp": 6,
    "metrics": {
      "Timestamp": 175594.04703,
      "AudioHandlers": 0,
      "AudioWorkletProcessors": 0,
      "Documents": 32,
      "Frames": 33,
      "JSEventListeners": 1915,
      "LayoutObjects": 3183,
      "MediaKeySessions": 0,
      "MediaKeys": 0,
      "Nodes": 3875,
      "Resources": 288,
      "ContextLifecycleStateObservers": 126,
      "V8PerContextDatas": 15,
      "WorkerGlobalScopes": 1,
      "UACSSResources": 0,
      "RTCPeerConnections": 0,
      "ResourceFetchers": 34,
      "AdSubframes": 0,
      "DetachedScriptStates": 5,
      "ArrayBufferContents": 619,
      "LayoutCount": 0,
      "RecalcStyleCount": 0,
      "LayoutDuration": 0,
      "RecalcStyleDuration": 0,
      "DevToolsCommandDuration": 0.002075,
      "ScriptDuration": 0.063341,
      "V8CompileDuration": 2e-05,
      "TaskDuration": 0.10754,
      "TaskOtherDuration": 0.042104,
      "ThreadTime": 0.11809,
      "ProcessTime": 5.301274,
      "JSHeapUsedSize": 70539176,
      "JSHeapTotalSize": 90849280,
      "FirstMeaningfulPaint": 175581.710988,
      "DomContentLoaded": 175581.346685,
      "NavigationStart": 175577.658679
    }
  },
  {
    "timestamp": 7,
    "metrics": {
      "Timestamp": 175595.050178,
      "AudioHandlers": 0,
      "AudioWorkletProcessors": 0,
      "Documents": 32,
      "Frames": 33,
      "JSEventListeners": 1915,
      "LayoutObjects": 3183,
      "MediaKeySessions": 0,
      "MediaKeys": 0,
      "Nodes": 3875,
      "Resources": 288,
      "ContextLifecycleStateObservers": 126,
      "V8PerContextDatas": 15,
      "WorkerGlobalScopes": 1,
      "UACSSResources": 0,
      "RTCPeerConnections": 0,
      "ResourceFetchers": 34,
      "AdSubframes": 0,
      "DetachedScriptStates": 5,
      "ArrayBufferContents": 619,
      "LayoutCount": 0,
      "RecalcStyleCount": 0,
      "LayoutDuration": 0,
      "RecalcStyleDuration": 0,
      "DevToolsCommandDuration": 0.00231,
      "ScriptDuration": 0.071199,
      "V8CompileDuration": 2e-05,
      "TaskDuration": 0.118401,
      "TaskOtherDuration": 0.044872,
      "ThreadTime": 0.130465,
      "ProcessTime": 5.31744,
      "JSHeapUsedSize": 70659888,
      "JSHeapTotalSize": 91111424,
      "FirstMeaningfulPaint": 175581.710988,
      "DomContentLoaded": 175581.346685,
      "NavigationStart": 175577.658679
    }
  },
  {
    "timestamp": 8,
    "metrics": {
      "Timestamp": 175596.053174,
      "AudioHandlers": 0,
      "AudioWorkletProcessors": 0,
      "Documents": 32,
      "Frames": 33,
      "JSEventListeners": 1915,
      "LayoutObjects": 3183,
      "MediaKeySessions": 0,
      "MediaKeys": 0,
      "Nodes": 3875,
      "Resources": 288,
      "ContextLifecycleStateObservers": 126,
      "V8PerContextDatas": 15,
      "WorkerGlobalScopes": 1,
      "UACSSResources": 0,
      "RTCPeerConnections": 0,
      "ResourceFetchers": 34,
      "AdSubframes": 0,
      "DetachedScriptStates": 5,
      "ArrayBufferContents": 619,
      "LayoutCount": 0,
      "RecalcStyleCount": 0,
      "LayoutDuration": 0,
      "RecalcStyleDuration": 0,
      "DevToolsCommandDuration": 0.002631,
      "ScriptDuration": 0.078374,
      "V8CompileDuration": 2e-05,
      "TaskDuration": 0.128219,
      "TaskOtherDuration": 0.047194,
      "ThreadTime": 0.141297,
      "ProcessTime": 5.331696,
      "JSHeapUsedSize": 70766556,
      "JSHeapTotalSize": 91111424,
      "FirstMeaningfulPaint": 175581.710988,
      "DomContentLoaded": 175581.346685,
      "NavigationStart": 175577.658679
    }
  },
  {
    "timestamp": 9,
    "metrics": {
      "Timestamp": 175597.056092,
      "AudioHandlers": 0,
      "AudioWorkletProcessors": 0,
      "Documents": 32,
      "Frames": 33,
      "JSEventListeners": 1916,
      "LayoutObjects": 3183,
      "MediaKeySessions": 0,
      "MediaKeys": 0,
      "Nodes": 3877,
      "Resources": 289,
      "ContextLifecycleStateObservers": 126,
      "V8PerContextDatas": 15,
      "WorkerGlobalScopes": 1,
      "UACSSResources": 0,
      "RTCPeerConnections": 0,
      "ResourceFetchers": 34,
      "AdSubframes": 0,
      "DetachedScriptStates": 5,
      "ArrayBufferContents": 619,
      "LayoutCount": 0,
      "RecalcStyleCount": 0,
      "LayoutDuration": 0,
      "RecalcStyleDuration": 0,
      "DevToolsCommandDuration": 0.002942,
      "ScriptDuration": 0.087964,
      "V8CompileDuration": 2e-05,
      "TaskDuration": 0.140722,
      "TaskOtherDuration": 0.049796,
      "ThreadTime": 0.154749,
      "ProcessTime": 5.348339,
      "JSHeapUsedSize": 70918076,
      "JSHeapTotalSize": 91111424,
      "FirstMeaningfulPaint": 175581.710988,
      "DomContentLoaded": 175581.346685,
      "NavigationStart": 175577.658679
    }
  }
]