[
  {
    "level": "INFO",
    "message": "{\"message\":{\"method\":\"Page.frameStartedNavigating\",\"params\":{\"frameId\":\"A8211EC4DCE7B7722CC0BC611FCBD102\",\"loaderId\":\"05DC23AD47D9F1D7645F3432E6EF9FED\",\"navigationType\":\"differentDocument\",\"url\":\"http://goo.gl/\"}},\"webview\":\"A8211EC4DCE7B7722CC0BC611FCBD102\"}",
    "timestamp": 1769508871161
  },
  {
    "level": "INFO",
    "message": "{\"message\":{\"method\":\"Page.frameStartedLoading\",\"params\":{\"frameId\":\"A8211EC4DCE7B7722CC0BC611FCBD102\"}},\"webview\":\"A8211EC4DCE7B7722CC0BC611FCBD102\"}",
    "timestamp": 1769508871162
  },
  {
    "level": "INFO",
    "message": "{\"message\":{\"method\":\"Network.requestWillBeSent\",\"params\":{\"documentURL\":\"http://goo.gl/\",\"frameId\":\"A8211EC4DCE7B7722CC0BC611FCBD102\",\"hasUserGesture\":false,\"initiator\":{\"type\":\"other\"},\"loaderId\":\"05DC23AD47D9F1D7645F3432E6EF9FED\",\"redirectHasExtraInfo\":false,\"request\":{\"headers\":{\"Upgrade-Insecure-Requests\":\"1\",\"User-Agent\":\"Mozilla/5.0 (Windows NT 10.0; Win64; x64) AppleWebKit/537.36 (KHTML, like Gecko) HeadlessChrome/144.0.0.0 Safari/537.36\"},\"initialPriority\":\"VeryHigh\",\"isSameSite\":true,\"method\":\"GET\",\"mixedContentType\":\"none\",\"referrerPolicy\":\"strict-origin-when-cross-origin\",\"url\":\"http://goo.gl/\"},\"requestId\":\"05DC23AD47D9F1D7645F3432E6EF9FED\",\"timestamp\":171388.890178,\"type\":\"Document\",\"wallTime\":1769508871.164177}},\"webview\":\"A8211EC4DCE7B7722CC0BC611FCBD102\"}",
    "timestamp": 1769508871166
  },
  {
    "level": "INFO",
    "message": "{\"message\":{\"method\":\"Network.requestWillBeSent\",\"params\":{\"documentURL\":\"https://goo.gl/\",\"frameId\":\"A8211EC4DCE7B7722CC0BC611FCBD102\",\"hasUserGesture\":false,\"initiator\":{\"type\":\"other\"},\"loaderId\":\"05DC23AD47D9F1D7645F3432E6EF9FED\",\"redirectHasExtraInfo\":false,\"redirectResponse\":{\"alternateProtocolUsage\":\"unspecifiedReason\",\"charset\":\"\",\"connectionId\":0,\"connectionReused\":false,\"encodedDataLength\":0,\"fromDiskCache\":false,\"fromPrefetchCache\":false,\"fromServiceWorker\":false,\"headers\":{\"Cross-Origin-Resource-Policy\":\"Cross-Origin\",\"Location\":\"https://goo.gl/\",\"Non-Authoritative-Reason\":\"HSTS\"},\"mimeType\":\"\",\"protocol\":\"http/1.1\",\"remoteIPAddress\":\"\",\"remotePort\":0,\"responseTime\":1.769508871170368e+12,\"securityState\":\"insecure\",\"status\":307,\"statusText\":\"Internal Redirect\",\"timing\":{\"connectEnd\":-1,\"connectStart\":-1,\"dnsEnd\":-1,\"dnsStart\":-1,\"proxyEnd\":-1,\"proxyStart\":-1,\"pushEnd\":0,\"pushStart\":0,\"receiveHeadersEnd\":0.169,\"receiveHeadersStart\":0.169,\"requestTime\":171388.896232,\"sendEnd\":0.169,\"sendStart\":0.169,\"sslEnd\":-1,\"sslStart\":-1,\"workerFetchStart\":-1,\"workerReady\":-1,\"workerRespondWithSettled\":-1,\"workerStart\":-1},\"url\":\"http://goo.gl/\"},\"request\":{\"headers\":{\"Upgrade-Insecure-Requests\":\"1\",\"User-Agent\":\"Mozilla/5.0 (Windows NT 10.0; Win64; x64) AppleWebKit/537.36 (KHTML, like Gecko) HeadlessChrome/144.0.0.0 Safari/537.36\"},\"initialPriority\":\"VeryHigh\",\"isSameSite\":true,\"method\":\"GET\",\"mixedContentType\":\"none\",\"referrerPolicy\":\"strict-origin-when-cross-origin\",\"url\":\"https://goo.gl/\"},\"requestId\":\"05DC23AD47D9F1D7645F3432E6EF9FED\",\"timestamp\":171388.898902,\"type\":\"Document\",\"wallTime\":1769508871.172932}},\"webview\":\"A8211EC4DCE7B7722CC0BC611FCBD102\"}",
    "timestamp": 1769508871178
  },
  {
    "level": "INFO",
    "message": "{\"message\":{\"method\":\"Network.requestWillBeSentExtraInfo\",\"params\":{\"associatedCookies\":[],\"connectTiming\":{\"requestTime\":171388.957898},\"headers\":{\":authority\":\"goo.gl\",\":method\":\"GET\",\":path\":\"/\",\":scheme\":\"https\",\"accept\":\"text/html,application/xhtml+xml,application/xml;q=0.9,image/avif,image/webp,image/apng,*/*;q=0.8,application/signed-exchange;v=b3;q=0.7\",\"accept-encoding\":\"gzip, deflate, br, zstd\",\"accept-language\":\"en-US,en;q=0.9\",\"priority\":\"u=0, i\",\"sec-ch-ua\":\"\\\"Not(A:Brand\\\";v=\\\"8\\\", \\\"Chromium\\\";v=\\\"144\\\", \\\"Google Chrome\\\";v=\\\"144\\\"\",\"sec-ch-ua-arch\":\"\\\"x86\\\"\",\"sec-ch-ua-bitness\":\"\\\"64\\\"\",\"sec-ch-ua-full-version-list\":\"\\\"Not(A:Brand\\\";v=\\\"8.0.0.0\\\", \\\"Chromium\\\";v=\\\"144.0.7559.97\\\", \\\"Google Chrome\\\";v=\\\"144.0.7559.97\\\"\",\"sec-ch-ua-mobile\":\"?0\",\"sec-ch-ua-model\":\"\\\"\\\"\",\"sec-ch-ua-platform\":\"\\\"Windows\\\"\",\"sec-ch-ua-platform-version\":\"\\\"19.0.0\\\"\",\"sec-ch-ua-wow64\":\"?0\",\"sec-fetch-dest\":\"document\",\"sec-fetch-mode\":\"navigate\",\"sec-fetch-site\":\"none\",\"sec-fetch-user\":\"?1\",\"upgrade-insecure-requests\":\"1\",\"user-agent\":\"Mozilla/5.0 (Windows NT 10.0; Win64; x64) AppleWebKit/537.36 (KHTML, like Gecko) HeadlessChrome/144.0.0.0 Safari/537.36\"},\"requestId\":\"05DC23AD47D9F1D7645F3432E6EF9FED\",\"siteHasCookieInOtherPartition\":false}},\"webview\":\"A8211EC4DCE7B7722CC0BC611FCBD102\"}",
    "timestamp": 1769508871233
  },
  {
    "level": "INFO",
    "message": "{\"message\":{\"method\":\"Network.responseReceivedExtraInfo\",\"params\":{\"blockedCookies\":[],\"cookiePartitionKey\":{\"hasCrossSiteAncestor\":false,\"topLevelSite\":\"https://goo.gl\"},\"cookiePartitionKeyOpaque\":false,\"exemptedCookies\":[],\"headers\":{\"accept-ch\":\"Sec-CH-UA-Arch, Sec-CH-UA-Bitness, Sec-CH-UA-Full-Version, Sec-CH-UA-Full-Version-List, Sec-CH-UA-Model, Sec-CH-UA-WoW64, Sec-CH-UA-Form-Factors, Sec-CH-UA-Platform, Sec-CH-UA-Platform-Version\",\"alt-svc\":\"h3=\\\":443\\\"; ma=2592000,h3-29=\\\":443\\\"; ma=2592000\",\"cache-control\":\"no-cache, no-store, max-age=0, must-revalidate\",\"content-encoding\":\"gzip\",\"content-security-policy\":\"script-src 'report-sample' 'nonce-ruYj7R4ab62ppZmG7tanUg' 'unsafe-inline';object-src 'none';base-uri 'self';report-uri /_/DurableDeepLinkUi/cspreport;worker-src 'self'\\nscript-src 'unsafe-inline' 'unsafe-eval' blob: data: 'self' https://apis.google.com https://ssl.gstatic.com https://www.google.com https://www.googletagmanager.com https://www.gstatic.com https://www.google-analytics.com https://www.googleapis.com/appsmarket/v2/installedApps/;report-uri /_/DurableDeepLinkUi/cspreport/allowlist\\nrequire-trusted-types-for 'script';report-uri /_/DurableDeepLinkUi/cspreport\",\"content-type\":\"text/html; charset=utf-8\",\"cross-origin-opener-policy\":\"unsafe-none\",\"date\":\"Tue, 27 Jan 2026 10:14:31 GMT\",\"expires\":\"Mon, 01 Jan 1990 00:00:00 GMT\",\"permissions-policy\":\"ch-ua-arch=*, ch-ua-bitness=*, ch-ua-full-version=*, ch-ua-full-version-list=*, ch-ua-model=*, ch-ua-wow64=*, ch-ua-form-factors=*, ch-ua-platform=*, ch-ua-platform-version=*\",\"pragma\":\"no-cache\",\"server\":\"ESF\",\"strict-transport-security\":\"max-age=31536000\",\"vary\":\"Sec-Fetch-Dest, Sec-Fetch-Mode, Sec-Fetch-Site\",\"x-content-type-options\":\"nosniff\",\"x-frame-options\":\"SAMEORIGIN\",\"x-xss-protection\":\"0\"},\"requestId\":\"05DC23AD47D9F1D7645F3432E6EF9FED\",\"resourceIPAddressSpace\":\"Public\",\"statusCode\":400}},\"webview\":\"A8211EC4DCE7B7722CC0BC611FCBD102\"}",
    "timestamp": 1769508871490
  },
  {
    "level": "INFO",
    "message": "{\"message\":{\"method\":\"Network.responseReceived\",\"params\":{\"frameId\":\"A8211EC4DCE7B7722CC0BC611FCBD102\",\"hasExtraInfo\":true,\"loaderId\":\"05DC23AD47D9F1D7645F3432E6EF9FED\",\"requestId\":\"05DC23AD47D9F1D7645F3432E6EF9FED\",\"response\":{\"alternateProtocolUsage\":\"unspecifiedReason\",\"charset\":\"utf-8\",\"connectionId\":118,\"connectionReused\":false,\"encodedDataLength\":1077,\"fromDiskCache\":false,\"fromPrefetchCache\":false,\"fromServiceWorker\":false,\"headers\":{\"accept-ch\":\"Sec-CH-UA-Arch, Sec-CH-UA-Bitness, Sec-CH-UA-Full-Version, Sec-CH-UA-Full-Version-List, Sec-CH-UA-Model, Sec-CH-UA-WoW64, Sec-CH-UA-Form-Factors, Sec-CH-UA-Platform, Sec-CH-UA-Platform-Version\",\"alt-svc\":\"h3=\\\":443\\\"; ma=2592000,h3-29=\\\":443\\\"; ma=2592000\",\"cache-control\":\"no-cache, no-store, max-age=0, must-revalidate\",\"content-encoding\":\"gzip\",\"content-security-policy\":\"script-src 'report-sample' 'nonce-ruYj7R4ab62ppZmG7tanUg' 'unsafe-inline';object-src 'none';base-uri 'self';report-uri /_/DurableDeepLinkUi/cspreport;worker-src 'self'\\nscript-src 'unsafe-inline' 'unsafe-eval' blob: data: 'self' https://apis.google.com https://ssl.gstatic.com https://www.google.com https://www.googletagmanager.com https://www.gstatic.com https://www.google-analytics.com https://www.googleapis.com/appsmarket/v2/installedApps/;report-uri /_/DurableDeepLinkUi/cspreport/allowlist\\nrequire-trusted-types-for 'script';report-uri /_/DurableDeepLinkUi/cspreport\",\"content-type\":\"text/html; charset=utf-8\",\"cross-origin-opener-policy\":\"unsafe-none\",\"date\":\"Tue, 27 Jan 2026 10:14:31 GMT\",\"expires\":\"Mon, 01 Jan 1990 00:00:00 GMT\",\"permissions-policy\":\"ch-ua-arch=*, ch-ua-bitness=*, ch-ua-full-version=*, ch-ua-full-version-list=*, ch-ua-model=*, ch-ua-wow64=*, ch-ua-form-factors=*, ch-ua-platform=*, ch-ua-platform-version=*\",\"pragma\":\"no-cache\",\"server\":\"ESF\",\"strict-transport-security\":\"max-age=31536000\",\"vary\":\"Sec-Fetch-Dest, Sec-Fetch-Mode, Sec-Fetch-Site\",\"x-content-type-options\":\"nosniff\",\"x-frame-options\":\"SAMEORIGIN\",\"x-xss-protection\":\"0\"},\"mimeType\":\"text/html\",\"protocol\":\"h2\",\"remoteIPAddress\":\"142.250.183.174\",\"remotePort\":443,\"responseTime\":1.76950887148823e+12,\"securityDetails\":{\"certificateId\":0,\"certificateTransparencyCompliance\":\"compliant\",\"cipher\":\"AES_128_GCM\",\"encryptedClientHello\":false,\"issuer\":\"WE2\",\"keyExchange\":\"\",\"keyExchangeGroup\":\"X25519MLKEM768\",\"protocol\":\"TLS 1.3\",\"sanList\":[\"*.google.com\",\"*.appengine.google.com\",\"*.bdn.dev\",\"*.origin-test.bdn.dev\",\"*.cloud.google.com\",\"*.crowdsource.google.com\",\"*.datacompute.google.com\",\"*.google.ca\",\"*.google.cl\",\"*.google.co.in\",\"*.google.co.jp\",\"*.google.co.uk\",\"*.google.com.ar\",\"*.google.com.au\",\"*.google.com.br\",\"*.google.com.co\",\"*.google.com.mx\",\"*.google.com.tr\",\"*.google.com.vn\",\"*.google.de\",\"*.google.es\",\"*.google.fr\",\"*.google.hu\",\"*.google.it\",\"*.google.nl\",\"*.google.pl\",\"*.google.pt\",\"*.googleapis.cn\",\"*.googlevideo.com\",\"*.gstatic.cn\",\"*.gstatic-cn.com\",\"googlecnapps.cn\",\"*.googlecnapps.cn\",\"googleapps-cn.com\",\"*.googleapps-cn.com\",\"gkecnapps.cn\",\"*.gkecnapps.cn\",\"googledownloads.cn\",\"*.googledownloads.cn\",\"recaptcha.net.cn\",\"*.recaptcha.net.cn\",\"recaptcha-cn.net\",\"*.recaptcha-cn.net\",\"widevine.cn\",\"*.widevine.cn\",\"ampproject.org.cn\",\"*.ampproject.org.cn\",\"ampproject.net.cn\",\"*.ampproject.net.cn\",\"google-analytics-cn.com\",\"*.google-analytics-cn.com\",\"googleadservices-cn.com\",\"*.googleadservices-cn.com\",\"googlevads-cn.com\",\"*.googlevads-cn.com\",\"googleapis-cn.com\",\"*.googleapis-cn.com\",\"googleoptimize-cn.com\",\"*.googleoptimize-cn.com\",\"doubleclick-cn.net\",\"*.doubleclick-cn.net\",\"*.fls.doubleclick-cn.net\",\"*.g.doubleclick-cn.net\",\"doubleclick.cn\",\"*.doubleclick.cn\",\"*.fls.doubleclick.cn\",\"*.g.doubleclick.cn\",\"dartsearch-cn.net\",\"*.dartsearch-cn.net\",\"googletraveladservices-cn.com\",\"*.googletraveladservices-cn.com\",\"googletagservices-cn.com\",\"*.googletagservices-cn.com\",\"googletagmanager-cn.com\",\"*.googletagmanager-cn.com\",\"googlesyndication-cn.com\",\"*.googlesyndication-cn.com\",\"*.safeframe.googlesyndication-cn.com\",\"app-measurement-cn.com\",\"*.app-measurement-cn.com\",\"gvt1-cn.com\",\"*.gvt1-cn.com\",\"gvt2-cn.com\",\"*.gvt2-cn.com\",\"2mdn-cn.net\",\"*.2mdn-cn.net\",\"googleflights-cn.net\",\"*.googleflights-cn.net\",\"admob-cn.com\",\"*.admob-cn.com\",\"*.gemini.cloud.google.com\",\"googlesandbox-cn.com\",\"*.googlesandbox-cn.com\",\"*.safenup.googlesandbox-cn.com\",\"*.gstatic.com\",\"*.metric.gstatic.com\",\"*.gvt1.com\",\"*.gcpcdn.gvt1.com\",\"*.gvt2.com\",\"*.gcp.gvt2.com\",\"*.url.google.com\",\"*.youtube-nocookie.com\",\"*.ytimg.com\",\"ai.android\",\"android.com\",\"*.android.com\",\"*.flash.android.com\",\"g.cn\",\"*.g.cn\",\"g.co\",\"*.g.co\",\"goo.gl\",\"www.goo.gl\",\"google-analytics.com\",\"*.google-analytics.com\",\"google.com\",\"googlecommerce.com\",\"*.googlecommerce.com\",\"ggpht.cn\",\"*.ggpht.cn\",\"urchin.com\",\"*.urchin.com\",\"youtu.be\",\"youtube.com\",\"*.youtube.com\",\"music.youtube.com\",\"*.music.youtube.com\",\"youtubeeducation.com\",\"*.youtubeeducation.com\",\"youtubekids.com\",\"*.youtubekids.com\",\"yt.be\",\"*.yt.be\",\"android.clients.google.com\",\"*.android.google.cn\",\"*.chrome.google.cn\",\"*.developers.google.cn\",\"*.aistudio.google.com\"],\"serverSignatureAlgorithm\":1027,\"signedCertificateTimestampList\":[{\"hashAlgorithm\":\"SHA-256\",\"logDescription\":\"DigiCert 'Sphinx2026h1'\",\"logId\":\"499C9B69DE1D7CECFC36DECD8764A6B85BAF0A878019D15552FBE9EB29DDF8C3\",\"origin\":\"Embedded in certificate\",\"signatureAlgorithm\":\"ECDSA\",\"signatureData\":\"3045022100E3307ADF2D294B56B19DC4FA3CD8CB7B5D2C182D7104975E8ADC731A0CC4EF9202200DC8C500F96FD0E9F3FFE4662466EEF6B9686D43661710BFB52459C3DF1CD012\",\"status\":\"Verified\",\"timestamp\":1.767041472657e+12},{\"hashAlgorithm\":\"SHA-256\",\"logDescription\":\"Google 'Xenon2026h1' log\",\"logId\":\"969764BF555897ADF743876837084277E9F03AD5F6A4F3366E46A43F0FCAA9C6\",\"origin\":\"Embedded in certificate\",\"signatureAlgorithm\":\"ECDSA\",\"signatureData\":\"3044022057FF97E3C498C1FF1C8AD3EF22E1977843B973812455A1073EF5722DC9A01C920220050A597E602F8051A17C9FA7F7EC40F55DD76A19D67A7963E5BFA76971EFC71B\",\"status\":\"Verified\",\"timestamp\":1.767041472693e+12}],\"subjectName\":\"*.google.com\",\"validFrom\":1767037870,\"validTo\":1774295469},\"securityState\":\"secure\",\"status\":400,\"statusText\":\"\",\"timing\":{\"connectEnd\":0,\"connectStart\":0,\"dnsEnd\":0,\"dnsStart\":0,\"proxyEnd\":-1,\"proxyStart\":-1,\"pushEnd\":0,\"pushStart\":0,\"receiveHeadersEnd\":256.572,\"receiveHeadersStart\":256.258,\"requestTime\":171388.957898,\"sendEnd\":0.958,\"sendStart\":0.706,\"sslEnd\":0,\"sslStart\":0,\"workerFetchStart\":-1,\"workerReady\":-1,\"workerRespondWithSettled\":-1,\"workerStart\":-1},\"url\":\"https://goo.gl/\"},\"timestamp\":171389.226769,\"type\":\"Document\"}},\"webview\":\"A8211EC4DCE7B7722CC0BC611FCBD102\"}",
    "timestamp": 1769508871503
  },
  {
    "level": "INFO",
    "message": "{\"message\":{\"method\":\"Page.frameNavigated\",\"params\":{\"frame\":{\"adFrameStatus\":{\"adFrameType\":\"none\"},\"crossOriginIsolatedContextType\":\"NotIsolated\",\"domainAndRegistry\":\"goo.gl\",\"gatedAPIFeatures\":[],\"id\":\"A8211EC4DCE7B7722CC0BC611FCBD102\",\"loaderId\":\"05DC23AD47D9F1D7645F3432E6EF9FED\",\"mimeType\":\"text/html\",\"secureContextType\":\"Secure\",\"securityOrigin\":\"https://goo.gl\",\"securityOriginDetails\":{\"isLocalhost\":false},\"url\":\"https://goo.gl/\"},\"type\":\"Navigation\"}},\"webview\":\"A8211EC4DCE7B7722CC0BC611FCBD102\"}",
    "timestamp": 1769508871523
  },
  {
    "level": "INFO",
    "message": "{\"message\":{\"method\":\"Network.policyUpdated\",\"params\":{}},\"webview\":\"A8211EC4DCE7B7722CC0BC611FCBD102\"}",
    "timestamp": 1769508871528
  },
  {
    "level": "INFO",
    "message": "{\"message\":{\"method\":\"Network.dataReceived\",\"params\":{\"dataLength\":9233,\"encodedDataLength\":0,\"requestId\":\"05DC23AD47D9F1D7645F3432E6EF9FED\",\"timestamp\":171389.251206}},\"webview\":\"A8211EC4DCE7B7722CC0BC611FCBD102\"}",
    "timestamp": 1769508871552
  },
  {
    "level": "INFO",
    "message": "{\"message\":{\"method\":\"Network.loadingFinished\",\"params\":{\"encodedDataLength\":7618,\"requestId\":\"05DC23AD47D9F1D7645F3432E6EF9FED\",\"timestamp\":171389.220418}},\"webview\":\"A8211EC4DCE7B7722CC0BC611FCBD102\"}",
    "timestamp": 1769508871556
  },
  {
    "level": "INFO",
    "message": "{\"message\":{\"method\":\"Page.domContentEventFired\",\"params\":{\"timestamp\":171389.2675}},\"webview\":\"A8211EC4DCE7B7722CC0BC611FCBD102\"}",
    "timestamp": 1769508871567
  },
  {
    "level": "INFO",
    "message": "{\"message\":{\"method\":\"Page.loadEventFired\",\"params\":{\"timestamp\":171389.269406}},\"webview\":\"A8211EC4DCE7B7722CC0BC611FCBD102\"}",
    "timestamp": 1769508871567
  },
  {
    "level": "INFO",
    "message": "{\"message\":{\"method\":\"Page.frameStoppedLoading\",\"params\":{\"frameId\":\"A8211EC4DCE7B7722CC0BC611FCBD102\"}},\"webview\":\"A8211EC4DCE7B7722CC0BC611FCBD102\"}",
    "timestamp": 1769508871569
  },
  {
    "level": "INFO",
    "message": "{\"message\":{\"method\":\"Network.requestWillBeSent\",\"params\":{\"documentURL\":\"https://goo.gl/\",\"frameId\":\"A8211EC4DCE7B7722CC0BC611FCBD102\",\"hasUserGesture\":false,\"initiator\":{\"type\":\"other\"},\"loaderId\":\"05DC23AD47D9F1D7645F3432E6EF9FED\",\"redirectHasExtraInfo\":false,\"request\":{\"headers\":{\"Referer\":\"https://goo.gl/\",\"User-Agent\":\"Mozilla/5.0 (Windows NT 10.0; Win64; x64) AppleWebKit/537.36 (KHTML, like Gecko) HeadlessChrome/144.0.0.0 Safari/537.36\",\"sec-ch-ua\":\"\\\"Not(A:Brand\\\";v=\\\"8\\\", \\\"Chromium\\\";v=\\\"144\\\", \\\"Google Chrome\\\";v=\\\"144\\\"\",\"sec-ch-ua-arch\":\"\\\"x86\\\"\",\"sec-ch-ua-bitness\":\"\\\"64\\\"\",\"sec-ch-ua-form-factors\":\"\\\"Desktop\\\"\",\"sec-ch-ua-full-version\":\"\\\"144.0.7559.97\\\"\",\"sec-ch-ua-full-version-list\":\"\\\"Not(A:Brand\\\";v=\\\"8.0.0.0\\\", \\\"Chromium\\\";v=\\\"144.0.7559.97\\\", \\\"Google Chrome\\\";v=\\\"144.0.7559.97\\\"\",\"sec-ch-ua-mobile\":\"?0\",\"sec-ch-ua-model\":\"\\\"\\\"\",\"sec-ch-ua-platform\":\"\\\"Windows\\\"\",\"sec-ch-ua-platform-version\":\"\\\"19.0.0\\\"\",\"sec-ch-ua-wow64\":\"?0\"},\"initialPriority\":\"High\",\"isSameSite\":true,\"method\":\"GET\",\"mixedContentType\":\"none\",\"referrerPolicy\":\"strict-origin-when-cross-origin\",\"url\":\"https://goo.gl/favicon.ico\"},\"requestId\":\"17612.3\",\"timestamp\":171389.297773,\"type\":\"Other\",\"wallTime\":1769508871.571892}},\"webview\":\"A8211EC4DCE7B7722CC0BC611FCBD102\"}",
    "timestamp": 1769508876575
  },
  {
    "level": "INFO",
    "message": "{\"message\":{\"method\":\"Network.requestWillBeSentExtraInfo\",\"params\":{\"associatedCookies\":[],\"clientSecurityState\":{\"initiatorIPAddressSpace\":\"Public\",\"initiatorIsSecureContext\":true,\"privateNetworkRequestPolicy\":\"PermissionBlock\"},\"connectTiming\":{\"requestTime\":171389.299428},\"headers\":{\":authority\":\"goo.gl\",\":method\":\"GET\",\":path\":\"/favicon.ico\",\":scheme\":\"https\",\"accept\":\"image/avif,image/webp,image/apng,image/svg+xml,image/*,*/*;q=0.8\",\"accept-encoding\":\"gzip, deflate, br, zstd\",\"accept-language\":\"en-US,en;q=0.9\",\"priority\":\"u=1, i\",\"referer\":\"https://goo.gl/\",\"sec-ch-ua\":\"\\\"Not(A:Brand\\\";v=\\\"8\\\", \\\"Chromium\\\";v=\\\"144\\\", \\\"Google Chrome\\\";v=\\\"144\\\"\",\"sec-ch-ua-arch\":\"\\\"x86\\\"\",\"sec-ch-ua-bitness\":\"\\\"64\\\"\",\"sec-ch-ua-form-factors\":\"\\\"Desktop\\\"\",\"sec-ch-ua-full-version\":\"\\\"144.0.7559.97\\\"\",\"sec-ch-ua-full-version-list\":\"\\\"Not(A:Brand\\\";v=\\\"8.0.0.0\\\", \\\"Chromium\\\";v=\\\"144.0.7559.97\\\", \\\"Google Chrome\\\";v=\\\"144.0.7559.97\\\"\",\"sec-ch-ua-mobile\":\"?0\",\"sec-ch-ua-model\":\"\\\"\\\"\",\"sec-ch-ua-platform\":\"\\\"Windows\\\"\",\"sec-ch-ua-platform-version\":\"\\\"19.0.0\\\"\",\"sec-ch-ua-wow64\":\"?0\",\"sec-fetch-dest\":\"image\",\"sec-fetch-mode\":\"no-cors\",\"sec-fetch-site\":\"same-origin\",\"user-agent\":\"Mozilla/5.0 (Windows NT 10.0; Win64; x64) AppleWebKit/537.36 (KHTML, like Gecko) HeadlessChrome/144.0.0.0 Safari/537.36\"},\"requestId\":\"17612.3\",\"siteHasCookieInOtherPartition\":false}},\"webview\":\"A8211EC4DCE7B7722CC0BC611FCBD102\"}",
    "timestamp": 1769508876575
  },
  {
    "level": "INFO",
    "message": "{\"message\":{\"method\":\"Network.responseReceivedExtraInfo\",\"params\":{\"blockedCookies\":[],\"cookiePartitionKey\":{\"hasCrossSiteAncestor\":false,\"topLevelSite\":\"https://goo.gl\"},\"cookiePartitionKeyOpaque\":false,\"exemptedCookies\":[],\"headers\":{\"accept-ch\":\"Sec-CH-UA-Arch, Sec-CH-UA-Bitness, Sec-CH-UA-Full-Version, Sec-CH-UA-Full-Version-List, Sec-CH-UA-Model, Sec-CH-UA-WoW64, Sec-CH-UA-Form-Factors, Sec-CH-UA-Platform, Sec-CH-UA-Platform-Version\",\"alt-svc\":\"h3=\\\":443\\\"; ma=2592000,h3-29=\\\":443\\\"; ma=2592000\",\"cache-control\":\"no-cache, no-store, max-age=0, must-revalidate\",\"content-length\":\"0\",\"content-security-policy\":\"script-src 'report-sample' 'nonce-sfdpGagTjM0Yt7LdmRsTbw' 'unsafe-inline';object-src 'none';base-uri 'self';report-uri /_/DurableDeepLinkUi/cspreport;worker-src 'self'\\nscript-src 'unsafe-inline' 'unsafe-eval' blob: data: 'self' https://apis.google.com https://ssl.gstatic.com https://www.google.com https://www.googletagmanager.com https://www.gstatic.com https://www.google-analytics.com https://www.googleapis.com/appsmarket/v2/installedApps/;report-uri /_/DurableDeepLinkUi/cspreport/allowlist\\nrequire-trusted-types-for 'script';report-uri /_/DurableDeepLinkUi/cspreport\",\"content-type\":\"application/binary\",\"cross-origin-opener-policy\":\"unsafe-none\",\"cross-origin-resource-policy\":\"same-site\",\"date\":\"Tue, 27 Jan 2026 10:14:32 GMT\",\"expires\":\"Mon, 01 Jan 1990 00:00:00 GMT\",\"location\":\"https://ssl.gstatic.com/mobilesdk/240501_mobilesdk/firebase_16dp.png\",\"permissions-policy\":\"ch-ua-arch=*, ch-ua-bitness=*, ch-ua-full-version=*, ch-ua-full-version-list=*, ch-ua-model=*, ch-ua-wow64=*, ch-ua-form-factors=*, ch-ua-platform=*, ch-ua-platform-version=*\",\"pragma\":\"no-cache\",\"server\":\"ESF\",\"strict-transport-security\":\"max-age=31536000\",\"vary\":\"Sec-Fetch-Dest, Sec-Fetch-Mode, Sec-Fetch-Site\",\"x-content-type-options\":\"nosniff\",\"x-frame-options\":\"SAMEORIGIN\",\"x-xss-protection\":\"0\"},\"requestId\":\"17612.3\",\"resourceIPAddressSpace\":\"Public\",\"statusCode\":301}},\"webview\":\"A8211EC4DCE7B7722CC0BC611FCBD102\"}",
    "timestamp": 1769508876576
  },
  {
    "level": "INFO",
    "message": "{\"message\":{\"method\":\"Network.requestWillBeSent\",\"params\":{\"documentURL\":\"https://goo.gl/\",\"frameId\":\"A8211EC4DCE7B7722CC0BC611FCBD102\",\"hasUserGesture\":false,\"initiator\":{\"type\":\"other\"},\"loaderId\":\"05DC23AD47D9F1D7645F3432E6EF9FED\",\"redirectHasExtraInfo\":true,\"redirectResponse\":{\"alternateProtocolUsage\":\"mainJobWonRace\",\"charset\":\"\",\"connectionId\":118,\"connectionReused\":true,\"encodedDataLength\":283,\"fromDiskCache\":false,\"fromPrefetchCache\":false,\"fromServiceWorker\":false,\"headers\":{\"accept-ch\":\"Sec-CH-UA-Arch, Sec-CH-UA-Bitness, Sec-CH-UA-Full-Version, Sec-CH-UA-Full-Version-List, Sec-CH-UA-Model, Sec-CH-UA-WoW64, Sec-CH-UA-Form-Factors, Sec-CH-UA-Platform, Sec-CH-UA-Platform-Version\",\"alt-svc\":\"h3=\\\":443\\\"; ma=2592000,h3-29=\\\":443\\\"; ma=2592000\",\"cache-control\":\"no-cache, no-store, max-age=0, must-revalidate\",\"content-length\":\"0\",\"content-security-policy\":\"script-src 'report-sample' 'nonce-sfdpGagTjM0Yt7LdmRsTbw' 'unsafe-inline';object-src 'none';base-uri 'self';report-uri /_/DurableDeepLinkUi/cspreport;worker-src 'self', script-src 'unsafe-inline' 'unsafe-eval' blob: data: 'self' https://apis.google.com https://ssl.gstatic.com https://www.google.com https://www.googletagmanager.com https://www.gstatic.com https://www.google-analytics.com https://www.googleapis.com/appsmarket/v2/installedApps/;report-uri /_/DurableDeepLinkUi/cspreport/allowlist, require-trusted-types-for 'script';report-uri /_/DurableDeepLinkUi/cspreport\",\"content-type\":\"application/binary\",\"cross-origin-opener-policy\":\"unsafe-none\",\"cross-origin-resource-policy\":\"same-site\",\"date\":\"Tue, 27 Jan 2026 10:14:32 GMT\",\"expires\":\"Mon, 01 Jan 1990 00:00:00 GMT\",\"location\":\"https://ssl.gstatic.com/mobilesdk/240501_mobilesdk/firebase_16dp.png\",\"permissions-policy\":\"ch-ua-arch=*, ch-ua-bitness=*, ch-ua-full-version=*, ch-ua-full-version-list=*, ch-ua-model=*, ch-ua-wow64=*, ch-ua-form-factors=*, ch-ua-platform=*, ch-ua-platform-version=*\",\"pragma\":\"no-cache\",\"server\":\"ESF\",\"strict-transport-security\":\"max-age=31536000\",\"vary\":\"Sec-Fetch-Dest, Sec-Fetch-Mode, Sec-Fetch-Site\",\"x-content-type-options\":\"nosniff\",\"x-frame-options\":\"SAMEORIGIN\",\"x-xss-protection\":\"0\"},\"mimeType\":\"application/binary\",\"protocol\":\"h2\",\"remoteIPAddress\":\"142.250.183.174\",\"remotePort\":443,\"responseTime\":1.769508872412339e+12,\"securityDetails\":{\"certificateId\":0,\"certificateTransparencyCompliance\":\"compliant\",\"cipher\":\"AES_128_GCM\",\"encryptedClientHello\":false,\"issuer\":\"WE2\",\"keyExchange\":\"\",\"keyExchangeGroup\":\"X25519MLKEM768\",\"protocol\":\"TLS 1.3\",\"sanList\":[\"*.google.com\",\"*.appengine.google.com\",\"*.bdn.dev\",\"*.origin-test.bdn.dev\",\"*.cloud.google.com\",\"*.crowdsource.google.com\",\"*.datacompute.google.com\",\"*.google.ca\",\"*.google.cl\",\"*.google.co.in\",\"*.google.co.jp\",\"*.google.co.uk\",\"*.google.com.ar\",\"*.google.com.au\",\"*.google.com.br\",\"*.google.com.co\",\"*.google.com.mx\",\"*.google.com.tr\",\"*.google.com.vn\",\"*.google.de\",\"*.google.es\",\"*.google.fr\",\"*.google.hu\",\"*.google.it\",\"*.google.nl\",\"*.google.pl\",\"*.google.pt\",\"*.googleapis.cn\",\"*.googlevideo.com\",\"*.gstatic.cn\",\"*.gstatic-cn.com\",\"googlecnapps.cn\",\"*.googlecnapps.cn\",\"googleapps-cn.com\",\"*.googleapps-cn.com\",\"gkecnapps.cn\",\"*.gkecnapps.cn\",\"googledownloads.cn\",\"*.googledownloads.cn\",\"recaptcha.net.cn\",\"*.recaptcha.net.cn\",\"recaptcha-cn.net\",\"*.recaptcha-cn.net\",\"widevine.cn\",\"*.widevine.cn\",\"ampproject.org.cn\",\"*.ampproject.org.cn\",\"ampproject.net.cn\",\"*.ampproject.net.cn\",\"google-analytics-cn.com\",\"*.google-analytics-cn.com\",\"googleadservices-cn.com\",\"*.googleadservices-cn.com\",\"googlevads-cn.com\",\"*.googlevads-cn.com\",\"googleapis-cn.com\",\"*.googleapis-cn.com\",\"googleoptimize-cn.com\",\"*.googleoptimize-cn.com\",\"doubleclick-cn.net\",\"*.doubleclick-cn.net\",\"*.fls.doubleclick-cn.net\",\"*.g.doubleclick-cn.net\",\"doubleclick.cn\",\"*.doubleclick.cn\",\"*.fls.doubleclick.cn\",\"*.g.doubleclick.cn\",\"dartsearch-cn.net\",\"*.dartsearch-cn.net\",\"googletraveladservices-cn.com\",\"*.googletraveladservices-cn.com\",\"googletagservices-cn.com\",\"*.googletagservices-cn.com\",\"googletagmanager-cn.com\",\"*.googletagmanager-cn.com\",\"googlesyndication-cn.com\",\"*.googlesyndication-cn.com\",\"*.safeframe.googlesyndication-cn.com\",\"app-measurement-cn.com\",\"*.app-measurement-cn.com\",\"gvt1-cn.com\",\"*.gvt1-cn.com\",\"gvt2-cn.com\",\"*.gvt2-cn.com\",\"2mdn-cn.net\",\"*.2mdn-cn.net\",\"googleflights-cn.net\",\"*.googleflights-cn.net\",\"admob-cn.com\",\"*.admob-cn.com\",\"*.gemini.cloud.google.com\",\"googlesandbox-cn.com\",\"*.googlesandbox-cn.com\",\"*.safenup.googlesandbox-cn.com\",\"*.gstatic.com\",\"*.metric.gstatic.com\",\"*.gvt1.com\",\"*.gcpcdn.gvt1.com\",\"*.gvt2.com\",\"*.gcp.gvt2.com\",\"*.url.google.com\",\"*.youtube-nocookie.com\",\"*.ytimg.com\",\"ai.android\",\"android.com\",\"*.android.com\",\"*.flash.android.com\",\"g.cn\",\"*.g.cn\",\"g.co\",\"*.g.co\",\"goo.gl\",\"www.goo.gl\",\"google-analytics.com\",\"*.google-analytics.com\",\"google.com\",\"googlecommerce.com\",\"*.googlecommerce.com\",\"ggpht.cn\",\"*.ggpht.cn\",\"urchin.com\",\"*.urchin.com\",\"youtu.be\",\"youtube.com\",\"*.youtube.com\",\"music.youtube.com\",\"*.music.youtube.com\",\"youtubeeducation.com\",\"*.youtubeeducation.com\",\"youtubekids.com\",\"*.youtubekids.com\",\"yt.be\",\"*.yt.be\",\"android.clients.google.com\",\"*.android.google.cn\",\"*.chrome.google.cn\",\"*.developers.google.cn\",\"*.aistudio.google.com\"],\"serverSignatureAlgorithm\":1027,\"signedCertificateTimestampList\":[{\"hashAlgorithm\":\"SHA-256\",\"logDescription\":\"DigiCert 'Sphinx2026h1'\",\"logId\":\"499C9B69DE1D7CECFC36DECD8764A6B85BAF0A878019D15552FBE9EB29DDF8C3\",\"origin\":\"Embedded in certificate\",\"signatureAlgorithm\":\"ECDSA\",\"signatureData\":\"3045022100E3307ADF2D294B56B19DC4FA3CD8CB7B5D2C182D7104975E8ADC731A0CC4EF9202200DC8C500F96FD0E9F3FFE4662466EEF6B9686D43661710BFB52459C3DF1CD012\",\"status\":\"Verified\",\"timestamp\":1.767041472657e+12},{\"hashAlgorithm\":\"SHA-256\",\"logDescription\":\"Google 'Xenon2026h1' log\",\"logId\":\"969764BF555897ADF743876837084277E9F03AD5F6A4F3366E46A43F0FCAA9C6\",\"origin\":\"Embedded in certificate\",\"signatureAlgorithm\":\"ECDSA\",\"signatureData\":\"3044022057FF97E3C498C1FF1C8AD3EF22E1977843B973812455A1073EF5722DC9A01C920220050A597E602F8051A17C9FA7F7EC40F55DD76A19D67A7963E5BFA76971EFC71B\",\"status\":\"Verified\",\"timestamp\":1.767041472693e+12}],\"subjectName\":\"*.google.com\",\"validFrom\":1767037870,\"validTo\":1774295469},\"securityState\":\"secure\",\"status\":301,\"statusText\":\"\",\"timing\":{\"connectEnd\":-1,\"connectStart\":-1,\"dnsEnd\":-1,\"dnsStart\":-1,\"proxyEnd\":-1,\"proxyStart\":-1,\"pushEnd\":0,\"pushStart\":0,\"receiveHeadersEnd\":839.155,\"receiveHeadersStart\":838.881,\"requestTime\":171389.299428,\"sendEnd\":2.685,\"sendStart\":2.383,\"sslEnd\":-1,\"sslStart\":-1,\"workerFetchStart\":-1,\"workerReady\":-1,\"workerRespondWithSettled\":-1,\"workerStart\":-1},\"url\":\"https://goo.gl/favicon.ico\"},\"request\":{\"headers\":{\"Referer\":\"https://goo.gl/\",\"User-Agent\":\"Mozilla/5.0 (Windows NT 10.0; Win64; x64) AppleWebKit/537.36 (KHTML, like Gecko) HeadlessChrome/144.0.0.0 Safari/537.36\"},\"initialPriority\":\"High\",\"isSameSite\":false,\"method\":\"GET\",\"mixedContentType\":\"none\",\"referrerPolicy\":\"strict-origin-when-cross-origin\",\"url\":\"https://ssl.gstatic.com/mobilesdk/240501_mobilesdk/firebase_16dp.png\"},\"requestId\":\"17612.3\",\"timestamp\":171390.141012,\"type\":\"Other\",\"wallTime\":1769508872.415322}},\"webview\":\"A8211EC4DCE7B7722CC0BC611FCBD102\"}",
    "timestamp": 1769508876576
  },
  {
    "level": "INFO",
    "message": "{\"message\":{\"method\":\"Network.requestWillBeSentExtraInfo\",\"params\":{\"associatedCookies\":[],\"clientSecurityState\":{\"initiatorIPAddressSpace\":\"Public\",\"initiatorIsSecureContext\":true,\"privateNetworkRequestPolicy\":\"PermissionBlock\"},\"connectTiming\":{\"requestTime\":171390.142119},\"headers\":{\":authority\":\"ssl.gstatic.com\",\":method\":\"GET\",\":path\":\"/mobilesdk/240501_mobilesdk/firebase_16dp.png\",\":scheme\":\"https\",\"accept\":\"image/avif,image/webp,image/apng,image/svg+xml,image/*,*/*;q=0.8\",\"accept-encoding\":\"gzip, deflate, br, zstd\",\"accept-language\":\"en-US,en;q=0.9\",\"priority\":\"u=1, i\",\"referer\":\"https://goo.gl/\",\"sec-ch-ua\":\"\\\"Not(A:Brand\\\";v=\\\"8\\\", \\\"Chromium\\\";v=\\\"144\\\", \\\"Google Chrome\\\";v=\\\"144\\\"\",\"sec-ch-ua-arch\":\"\\\"x86\\\"\",\"sec-ch-ua-bitness\":\"\\\"64\\\"\",\"sec-ch-ua-form-factors\":\"\\\"Desktop\\\"\",\"sec-ch-ua-full-version\":\"\\\"144.0.7559.97\\\"\",\"sec-ch-ua-full-version-list\":\"\\\"Not(A:Brand\\\";v=\\\"8.0.0.0\\\", \\\"Chromium\\\";v=\\\"144.0.7559.97\\\", \\\"Google Chrome\\\";v=\\\"144.0.7559.97\\\"\",\"sec-ch-ua-mobile\":\"?0\",\"sec-ch-ua-model\":\"\\\"\\\"\",\"sec-ch-ua-platform\":\"\\\"Windows\\\"\",\"sec-ch-ua-platform-version\":\"\\\"19.0.0\\\"\",\"sec-ch-ua-wow64\":\"?0\",\"sec-fetch-dest\":\"image\",\"sec-fetch-mode\":\"no-cors\",\"sec-fetch-site\":\"cross-site\",\"sec-fetch-storage-access\":\"active\",\"user-agent\":\"Mozilla/5.0 (Windows NT 10.0; Win64; x64) AppleWebKit/537.36 (KHTML, like Gecko) HeadlessChrome/144.0.0.0 Safari/537.36\",\"x-browser-channel\":\"stable\",\"x-browser-copyright\":\"Copyright 2026 Google LLC. All Rights reserved.\",\"x-browser-validation\":\"d8JhDaoX8b/ShTRrHDjGiWOeFok=\",\"x-browser-year\":\"2026\"},\"requestId\":\"17612.3\",\"siteHasCookieInOtherPartition\":false}},\"webview\":\"A8211EC4DCE7B7722CC0BC611FCBD102\"}",
    "timestamp": 1769508876576
  },
  {
    "level": "INFO",
    "message": "{\"message\":{\"method\":\"Network.responseReceivedExtraInfo\",\"params\":{\"blockedCookies\":[],\"cookiePartitionKey\":{\"hasCrossSiteAncestor\":true,\"topLevelSite\":\"https://goo.gl\"},\"cookiePartitionKeyOpaque\":false,\"exemptedCookies\":[],\"headers\":{\"accept-ranges\":\"bytes\",\"age\":\"560849\",\"alt-svc\":\"h3=\\\":443\\\"; ma=2592000,h3-29=\\\":443\\\"; ma=2592000\",\"cache-control\":\"public, max-age=31536000\",\"content-length\":\"480\",\"content-security-policy-report-only\":\"require-trusted-types-for 'script'; report-uri https://csp.withgoogle.com/csp/mobilesdk-devrel-eng\",\"content-type\":\"image/png\",\"cross-origin-opener-policy\":\"same-origin; report-to=\\\"mobilesdk-devrel-eng\\\"\",\"cross-origin-resource-policy\":\"cross-origin\",\"date\":\"Tue, 20 Jan 2026 22:27:03 GMT\",\"expires\":\"Wed, 20 Jan 2027 22:27:03 GMT\",\"last-modified\":\"Wed, 01 May 2024 19:28:00 GMT\",\"report-to\":\"{\\\"group\\\":\\\"mobilesdk-devrel-eng\\\",\\\"max_age\\\":2592000,\\\"endpoints\\\":[{\\\"url\\\":\\\"https://csp.withgoogle.com/csp/report-to/mobilesdk-devrel-eng\\\"}]}\",\"server\":\"sffe\",\"vary\":\"Origin\",\"x-content-type-options\":\"nosniff\",\"x-xss-protection\":\"0\"},\"requestId\":\"17612.3\",\"resourceIPAddressSpace\":\"Public\",\"statusCode\":200}},\"webview\":\"A8211EC4DCE7B7722CC0BC611FCBD102\"}",
    "timestamp": 1769508876577
  },
  {
    "level": "INFO",
    "message": "{\"message\":{\"method\":\"Network.responseReceived\",\"params\":{\"frameId\":\"A8211EC4DCE7B7722CC0BC611FCBD102\",\"hasExtraInfo\":true,\"loaderId\":\"05DC23AD47D9F1D7645F3432E6EF9FED\",\"requestId\":\"17612.3\",\"response\":{\"alternateProtocolUsage\":\"unspecifiedReason\",\"charset\":\"\",\"connectionId\":152,\"connectionReused\":false,\"encodedDataLength\":1023,\"fromDiskCache\":false,\"fromPrefetchCache\":false,\"fromServiceWorker\":false,\"headers\":{\"accept-ranges\":\"bytes\",\"age\":\"560849\",\"alt-svc\":\"h3=\\\":443\\\"; ma=2592000,h3-29=\\\":443\\\"; ma=2592000\",\"cache-control\":\"public, max-age=31536000\",\"content-length\":\"480\",\"content-security-policy-report-only\":\"require-trusted-types-for 'script'; report-uri https://csp.withgoogle.com/csp/mobilesdk-devrel-eng\",\"content-type\":\"image/png\",\"cross-origin-opener-policy\":\"same-origin; report-to=\\\"mobilesdk-devrel-eng\\\"\",\"cross-origin-resource-policy\":\"cross-origin\",\"date\":\"Tue, 20 Jan 2026 22:27:03 GMT\",\"expires\":\"Wed, 20 Jan 2027 22:27:03 GMT\",\"last-modified\":\"Wed, 01 May 2024 19:28:00 GMT\",\"report-to\":\"{\\\"group\\\":\\\"mobilesdk-devrel-eng\\\",\\\"max_age\\\":2592000,\\\"endpoints\\\":[{\\\"url\\\":\\\"https://csp.withgoogle.com/csp/report-to/mobilesdk-devrel-eng\\\"}]}\",\"server\":\"sffe\",\"vary\":\"Origin\",\"x-content-type-options\":\"nosniff\",\"x-xss-protection\":\"0\"},\"mimeType\":\"image/png\",\"protocol\":\"h2\",\"remoteIPAddress\":\"142.250.67.35\",\"remotePort\":443,\"responseTime\":1.769508872547324e+12,\"securityState\":\"unknown\",\"status\":200,\"statusText\":\"\",\"timing\":{\"connectEnd\":47.071,\"connectStart\":8.671,\"dnsEnd\":8.381,\"dnsStart\":1.223,\"proxyEnd\":-1,\"proxyStart\":-1,\"pushEnd\":0,\"pushStart\":0,\"receiveHeadersEnd\":131.97,\"receiveHeadersStart\":131.17,\"requestTime\":171390.142119,\"sendEnd\":47.784,\"sendStart\":47.42,\"sslEnd\":47.057,\"sslStart\":16.485,\"workerFetchStart\":-1,\"workerReady\":-1,\"workerRespondWithSettled\":-1,\"workerStart\":-1},\"url\":\"https://ssl.gstatic.com/mobilesdk/240501_mobilesdk/firebase_16dp.png\"},\"timestamp\":171390.276737,\"type\":\"Other\"}},\"webview\":\"A8211EC4DCE7B7722CC0BC611FCBD102\"}",
    "timestamp": 1769508876577
  },
  {
    "level": "INFO",
    "message": "{\"message\":{\"method\":\"Network.dataReceived\",\"params\":{\"dataLength\":480,\"encodedDataLength\":0,\"requestId\":\"17612.3\",\"timestamp\":171390.27687}},\"webview\":\"A8211EC4DCE7B7722CC0BC611FCBD102\"}",
    "timestamp": 1769508876577
  },
  {
    "level": "INFO",
    "message": "{\"message\":{\"method\":\"Network.loadingFinished\",\"params\":{\"encodedDataLength\":1023,\"requestId\":\"17612.3\",\"timestamp\":171390.275228}},\"webview\":\"A8211EC4DCE7B7722CC0BC611FCBD102\"}",
    "timestamp": 1769508876577
  }
]