[
  {
    "timestamp": 0,
    "metrics": {
      "Timestamp": 174057.008615,
      "AudioHandlers": 0,
      "AudioWorkletProcessors": 0,
      "Documents": 3,
      "Frames": 4,
      "JSEventListeners": 19,
      "LayoutObjects": 277,
      "MediaKeySessions": 0,
      "MediaKeys": 0,
      "Nodes": 747,
      "Resources": 21,
      "ContextLifecycleStateObservers": 8,
      "V8PerContextDatas": 1,
      "WorkerGlobalScopes": 0,
      "UACSSResources": 0,
      "RTCPeerConnections": 0,
      "ResourceFetchers": 3,
      "AdSubframes": 0,
      "DetachedScriptStates": 0,
      "ArrayBufferContents": 0,
      "LayoutCount": 0,
      "RecalcStyleCount": 0,
      "LayoutDuration": 0,
      "RecalcStyleDuration": 0,
      "DevToolsCommandDuration": 9.9e-05,
      "ScriptDuration": 0,
      "V8CompileDuration": 0,
      "TaskDuration": 0.000122,
      "TaskOtherDuration": 2.3e-05,
      "ThreadTime": 0,
      "ProcessTime": 0.25,
      "JSHeapUsedSize": 661912,
      "JSHeapTotalSize": 1835008,
      "FirstMeaningfulPaint": 174050.057017,
      "DomContentLoaded": 174050.049228,
      "NavigationStart": 174049.22415
    }
  },
  {
    "timestamp": 1,
    "metrics": {
      "Timestamp": 174058.011958,
      "AudioHandlers": 0,
      "AudioWorkletProcessors": 0,
      "Documents": 3,
      "Frames": 4,
      "JSEventListeners": 19,
      "LayoutObjects": 277,
      "MediaKeySessions": 0,
      "MediaKeys": 0,
      "Nodes": 747,
      "Resources": 21,
      "ContextLifecycleStateObservers": 8,
      "V8PerContextDatas": 1,
      "WorkerGlobalScopes": 0,
      "UACSSResources": 0,
      "RTCPeerConnections": 0,
      "ResourceFetchers": 3,
      "AdSubframes": 0,
      "DetachedScriptStates": 0,
      "ArrayBufferContents": 0,
      "LayoutCount": 0,
      "RecalcStyleCount": 0,
      "LayoutDuration": 0,
      "RecalcStyleDuration": 0,
      "DevToolsCommandDuration": 0.000314,
      "ScriptDuration": 0,
      "V8CompileDuration": 0,
      "TaskDuration": 0.000384,
      "TaskOtherDuration": 7e-05,
      "ThreadTime": 0.145481,
      "ProcessTime": 0.201564,
      "JSHeapUsedSize": 662008,
      "JSHeapTotalSize": 1835008,
      "FirstMeaningfulPaint": 174050.057017,
      "DomContentLoaded": 174050.049228,
      "NavigationStart": 174049.22415
    }
  },
  {
    "timestamp": 2,
    "metrics": {
      "Timestamp": 174059.015775,
      "AudioHandlers": 0,
      "AudioWorkletProcessors": 0,
      "Documents": 3,
      "Frames": 4,
      "JSEventListeners": 19,
      "LayoutObjects": 277,
      "MediaKeySessions": 0,
      "MediaKeys": 0,
      "Nodes": 747,
      "Resources": 21,
      "ContextLifecycleStateObservers": 8,
      "V8PerContextDatas": 1,
      "WorkerGlobalScopes": 0,
      "UACSSResources": 0,
      "RTCPeerConnections": 0,
      "ResourceFetchers": 3,
      "AdSubframes": 0,
      "DetachedScriptStates": 0,
      "ArrayBufferContents": 0,
      "LayoutCount": 0,
      "RecalcStyleCount": 0,
      "LayoutDuration": 0,
      "RecalcStyleDuration": 0,
      "DevToolsCommandDuration": 0.000646,
      "ScriptDuration": 0,
      "V8CompileDuration": 0,
      "TaskDuration": 0.00076,
      "TaskOtherDuration": 0.000114,
      "ThreadTime": 0.145884,
      "ProcessTime": 0.202084,
      "JSHeapUsedSize": 662104,
      "JSHeapTotalSize": 1835008,
      "FirstMeaningfulPaint": 174050.057017,
      "DomContentLoaded": 174050.049228,
      "NavigationStart": 174049.22415
    }
  },
  {
    "timestamp": 3,
    "metrics": {
      "Timestamp": 174060.019124,
      "AudioHandlers": 0,
      "AudioWorkletProcessors": 0,
      "Documents": 3,
      "Frames": 4,
      "JSEventListeners": 19,
      "LayoutObjects": 277,
      "MediaKeySessions": 0,
      "MediaKeys": 0,
      "Nodes": 747,
      "Resources": 21,
      "ContextLifecycleStateObservers": 8,
      "V8PerContextDatas": 1,
      "WorkerGlobalScopes": 0,
      "UACSSResources": 0,
      "RTCPeerConnections": 0,
      "ResourceFetchers": 3,
      "AdSubframes": 0,
      "DetachedScriptStates": 0,
      "ArrayBufferContents": 0,
      "LayoutCount": 0,
      "RecalcStyleCount": 0,
      "LayoutDuration": 0,
      "RecalcStyleDuration": 0,
      "DevToolsCommandDuration": 0.000951,
      "ScriptDuration": 0,
      "V8CompileDuration": 0,
      "TaskDuration": 0.001759,
      "TaskOtherDuration": 0.000808,
      "ThreadTime": 0.147027,
      "ProcessTime": 0.203502,
      "JSHeapUsedSize": 662200,
      "JSHeapTotalSize": 1835008,
      "FirstMeaningfulPaint": 174050.057017,
      "DomContentLoaded": 174050.049228,
      "NavigationStart": 174049.22415
    }
  },
  {
    "timestamp": 4,
    "metrics": {
      "Timestamp": 174061.022202,
      "AudioHandlers": 0,
      "AudioWorkletProcessors": 0,
      "Documents": 3,
      "Frames": 4,
      "JSEventListeners": 19,
      "LayoutObjects": 277,
      "MediaKeySessions": 0,
      "MediaKeys": 0,
      "Nodes": 747,
      "Resources": 21,
      "ContextLifecycleStateObservers": 8,
      "V8PerContextDatas": 1,
      "WorkerGlobalScopes": 0,
      "UACSSResources": 0,
      "RTCPeerConnections": 0,
      "ResourceFetchers": 3,
      "AdSubframes": 0,
      "DetachedScriptStates": 0,
      "ArrayBufferContents": 0,
      "LayoutCount": 0,
      "RecalcStyleCount": 0,
      "LayoutDuration": 0,
      "RecalcStyleDuration": 0,
      "DevToolsCommandDuration": 0.001283,
      "ScriptDuration": 0,
      "V8CompileDuration": 0,
      "TaskDuration": 0.0022,
      "TaskOtherDuration": 0.000917,
      "ThreadTime": 0.147533,
      "ProcessTime": 0.204156,
      "JSHeapUsedSize": 662296,
      "JSHeapTotalSize": 1835008,
      "FirstMeaningfulPaint": 174050.057017,
      "DomContentLoaded": 174050.049228,
      "NavigationStart": 174049.22415
    }
  },
  {
    "timestamp": 5,
    "metrics": {
      "Timestamp": 174062.02529,
      "AudioHandlers": 0,
      "AudioWorkletProcessors": 0,
      "Documents": 3,
      "Frames": 4,
      "JSEventListeners": 19,
      "LayoutObjects": 277,
      "MediaKeySessions": 0,
      "MediaKeys": 0,
      "Nodes": 747,
      "Resources": 21,
      "ContextLifecycleStateObservers": 8,
      "V8PerContextDatas": 1,
      "WorkerGlobalScopes": 0,
      "UACSSResources": 0,
      "RTCPeerConnections": 0,
      "ResourceFetchers": 3,
      "AdSubframes": 0,
      "DetachedScriptStates": 0,
      "ArrayBufferContents": 0,
      "LayoutCount": 0,
      "RecalcStyleCount": 0,
      "LayoutDuration": 0,
      "RecalcStyleDuration": 0,
      "DevToolsCommandDuration": 0.001656,
      "ScriptDuration": 0,
      "V8CompileDuration": 0,
      "TaskDuration": 0.002727,
      "TaskOtherDuration": 0.001071,
      "ThreadTime": 0.148138,
      "ProcessTime": 0.20599,
      "JSHeapUsedSize": 662392,
      "JSHeapTotalSize": 1835008,
      "FirstMeaningfulPaint": 174050.057017,
      "DomContentLoaded": 174050.049228,
      "NavigationStart": 174049.22415
    }
  },
  {
    "timestamp": 6,
    "metrics": {
      "Timestamp": 174063.027992,
      "AudioHandlers": 0,
      "AudioWorkletProcessors": 0,
      "Documents": 3,
      "Frames": 4,
      "JSEventListeners": 19,
      "LayoutObjects": 277,
      "MediaKeySessions": 0,
      "MediaKeys": 0,
      "Nodes": 747,
      "Resources": 21,
      "ContextLifecycleStateObservers": 8,
      "V8PerContextDatas": 1,
      "WorkerGlobalScopes": 0,
      "UACSSResources": 0,
      "RTCPeerConnections": 0,
      "ResourceFetchers": 3,
      "AdSubframes": 0,
      "DetachedScriptStates": 0,
      "ArrayBufferContents": 0,
      "LayoutCount": 0,
      "RecalcStyleCount": 0,
      "LayoutDuration": 0,
      "RecalcStyleDuration": 0,
      "DevToolsCommandDuration": 0.001858,
      "ScriptDuration": 0,
      "V8CompileDuration": 0,
      "TaskDuration": 0.002975,
      "TaskOtherDuration": 0.001117,
      "ThreadTime": 0.148415,
      "ProcessTime": 0.206489,
      "JSHeapUsedSize": 662488,
      "JSHeapTotalSize": 1835008,
      "FirstMeaningfulPaint": 174050.057017,
      "DomContentLoaded": 174050.049228,
      "NavigationStart": 174049.22415
    }
  },
  {
    "timestamp": 7,
    "metrics": {
      "Timestamp": 174064.030853,
      "AudioHandlers": 0,
      "AudioWorkletProcessors": 0,
      "Documents": 3,
      "Frames": 4,
      "JSEventListeners": 19,
      "LayoutObjects": 277,
      "MediaKeySessions": 0,
      "MediaKeys": 0,
      "Nodes": 747,
      "Resources": 21,
      "ContextLifecycleStateObservers": 8,
      "V8PerContextDatas": 1,
      "WorkerGlobalScopes": 0,
      "UACSSResources": 0,
      "RTCPeerConnections": 0,
      "ResourceFetchers": 3,
      "AdSubframes": 0,
      "DetachedScriptStates": 0,
      "ArrayBufferContents": 0,
      "LayoutCount": 0,
      "RecalcStyleCount": 0,
      "LayoutDuration": 0,
      "RecalcStyleDuration": 0,
      "DevToolsCommandDuration": 0.002144,
      "ScriptDuration": 0,
      "V8CompileDuration": 0,
      "TaskDuration": 0.003301,
      "TaskOtherDuration": 0.001157,
      "ThreadTime": 0.148768,
      "ProcessTime": 0.206953,
      "JSHeapUsedSize": 662584,
      "JSHeapTotalSize": 1835008,
      "FirstMeaningfulPaint": 174050.057017,
      "DomContentLoaded": 174050.049228,
      "NavigationStart": 174049.22415
    }
  },
  {
    "timestamp": 8,
    "metrics": {
      "Timestamp": 174065.033615,
      "AudioHandlers": 0,
      "AudioWorkletProcessors": 0,
      "Documents": 3,
      "Frames": 4,
      "JSEventListeners": 19,
      "LayoutObjects": 277,
      "MediaKeySessions": 0,
      "MediaKeys": 0,
      "Nodes": 747,
      "Resources": 21,
      "ContextLifecycleStateObservers": 8,
      "V8PerContextDatas": 1,
      "WorkerGlobalScopes": 0,
      "UACSSResources": 0,
      "RTCPeerConnections": 0,
      "ResourceFetchers": 3,
      "AdSubframes": 0,
      "DetachedScriptStates": 0,
      "ArrayBufferContents": 0,
      "LayoutCount": 0,
      "RecalcStyleCount": 0,
      "LayoutDuration": 0,
      "RecalcStyleDuration": 0,
      "DevToolsCommandDuration": 0.002439,
      "ScriptDuration": 0,
      "V8CompileDuration": 0,
      "TaskDuration": 0.003637,
      "TaskOtherDuration": 0.001198,
      "ThreadTime": 0.149133,
      "ProcessTime": 0.207424,
      "JSHeapUsedSize": 662680,
      "JSHeapTotalSize": 1835008,
      "FirstMeaningfulPaint": 174050.057017,
      "DomContentLoaded": 174050.049228,
      "NavigationStart": 174049.22415
    }
  },
  {
    "timestamp": 9,
    "metrics": {
      "Timestamp": 174066.036527,
      "AudioHandlers": 0,
      "AudioWorkletProcessors": 0,
      "Documents": 3,
      "Frames": 4,
      "JSEventListeners": 19,
      "LayoutObjects": 277,
      "MediaKeySessions": 0,
      "MediaKeys": 0,
      "Nodes": 747,
      "Resources": 21,
      "ContextLifecycleStateObservers": 8,
      "V8PerContextDatas": 1,
      "WorkerGlobalScopes": 0,
      "UACSSResources": 0,
      "RTCPeerConnections": 0,
      "ResourceFetchers": 3,
      "AdSubframes": 0,
      "DetachedScriptStates": 0,
      "ArrayBufferContents": 0,
      "LayoutCount": 0,
      "RecalcStyleCount": 0,
      "LayoutDuration": 0,
      "RecalcStyleDuration": 0,
      "DevToolsCommandDuration": 0.002788,
      "ScriptDuration": 0,
      "V8CompileDuration": 0,
      "TaskDuration": 0.004032,
      "TaskOtherDuration": 0.001244,
      "ThreadTime": 0.149558,
      "ProcessTime": 0.207988,
      "JSHeapUsedSize": 662776,
      "JSHeapTotalSize": 1835008,
      "FirstMeaningfulPaint": 174050.057017,
      "DomContentLoaded": 174050.049228,
      "NavigationStart": 174049.22415
    }
  }
]